zero/__init__.py
zero/als.py
zero/als2.py
zero/als3.py
zero/balse.py
zero/cfm.py
zero/chrono.py
zero/dataset.py
zero/efa.py
zero/fma.py
zero/gbr.py
zero/knn.py
zero/knn0.py
zero/knn2.py
zero/lasso.py
zero/lasso0.py
zero/nmf.py
zero/pca.py
zero/recommendation_algorithm.py
zero/sgd.py
zero/sgd0.py
zero/sgd2.py
zero/side.py
zero/ssvd.py
zero/svd.py
zero/svd2.py
zero/tests/__init__.py
zero/tests/test_zero.py
zero/values.py
zero/wals.py
zero/xals.py
zero/zero.py
mangaki_zero-1.1.0.dist-info/LICENSE
mangaki_zero-1.1.0.dist-info/WHEEL
mangaki_zero-1.1.0.dist-info/METADATA
mangaki_zero-1.1.0.dist-info/RECORD
