Metadata-Version: 2.1
Name: mangaki-zero
Version: 1.1.0
Summary: Mangaki's recommandation algorithms
Home-page: http://research.mangaki.fr
License: GPL-3.0
Keywords: machine learning,recommandation,mangaki,recommender systems,algorithms
Author: Jill-Jênn Vie
Author-email: vie@jill-jenn.net
Requires-Python: >=3.7.1
Classifier: License :: OSI Approved :: GNU General Public License v3 (GPLv3)
Classifier: Programming Language :: Python :: 3
Classifier: Programming Language :: Python :: 3.8
Classifier: Programming Language :: Python :: 3.9
Provides-Extra: deep
Provides-Extra: external
Provides-Extra: fm
Requires-Dist: fastFM; extra == "fm"
Requires-Dist: numpy (>=1.20,<2.0)
Requires-Dist: pandas (>=1.3,<1.3.4)
Requires-Dist: pywFM; extra == "fm"
Requires-Dist: scikit-learn (>=1.0,<2.0)
Requires-Dist: scipy (>=1.4,<2.0)
Requires-Dist: surprise; extra == "external"
Requires-Dist: tensorflow; extra == "deep"
Project-URL: Documentation, https://github.com/mangaki/zero
